light_captcha/__init__.py
light_captcha/generator.py
light_captcha/fonts/Vazirmatn-Regular.ttf
light_captcha-0.0.3.dist-info/licenses/LICENSE
light_captcha-0.0.3.dist-info/METADATA
light_captcha-0.0.3.dist-info/WHEEL
light_captcha-0.0.3.dist-info/top_level.txt
light_captcha-0.0.3.dist-info/RECORD
