Metadata-Version: 2.4
Name: light-captcha
Version: 0.0.3
Summary: A lightweight CAPTCHA generator for Persian and English digits
Home-page: https://github.com/COD332/light-captcha
Author: Alireza Esameilzadeh
License-Expression: MIT
Project-URL: Homepage, https://github.com/COD332/light-captcha
Project-URL: Repository, https://github.com/COD332/light-captcha
Project-URL: Issues, https://github.com/COD332/light-captcha/issues
Keywords: captcha,persian,english,security,image,generation
Classifier: Development Status :: 5 - Production/Stable
Classifier: Intended Audience :: Developers
Classifier: Operating System :: OS Independent
Classifier: Programming Language :: Python :: 3
Classifier: Programming Language :: Python :: 3.7
Classifier: Programming Language :: Python :: 3.8
Classifier: Programming Language :: Python :: 3.9
Classifier: Programming Language :: Python :: 3.10
Classifier: Programming Language :: Python :: 3.11
Classifier: Programming Language :: Python :: 3.12
Classifier: Topic :: Software Development :: Libraries :: Python Modules
Classifier: Topic :: Security
Classifier: Topic :: Multimedia :: Graphics
Requires-Python: >=3.7
License-File: LICENSE
Requires-Dist: Pillow>=8.0.0
Requires-Dist: importlib_resources>=1.3.0; python_version < "3.9"
Dynamic: home-page
Dynamic: license-file
Dynamic: requires-python
